external_urls
