Metadata-Version: 1.1
Name: django-external-urls
Version: 0.3
Summary: Track external links with a signal on click.
Home-page: https://github.com/piran/django-external-urls
Author: Rich Atkinson, Piran Digital
Author-email: rich@piran.com.au
License: BSD
Download-URL: https://github.com/piran/django-external-urls/archive/0.3.zip
Keywords: django,external url,redirect
Platform: UNKNOWN
Classifier: Environment :: Web Environment
Classifier: Programming Language :: Python
Classifier: Framework :: Django
Classifier: License :: OSI Approved :: BSD License
Classifier: Topic :: Software Development :: Libraries :: Application Frameworks
Classifier: Topic :: Software Development :: Libraries :: Python Modules
